pyfseconomy/__init__.py
pyfseconomy/aircraft.py
pyfseconomy/airports.py
pyfseconomy/client.py
pyfseconomy/icaodata.csv
pyfseconomy/utils.py
pyfseconomy-0.3.0.dist-info/LICENSE
pyfseconomy-0.3.0.dist-info/METADATA
pyfseconomy-0.3.0.dist-info/WHEEL
pyfseconomy-0.3.0.dist-info/top_level.txt
pyfseconomy-0.3.0.dist-info/RECORD
