Metadata-Version: 2.1
Name: pyfseconomy
Version: 0.3.0
Summary: Library for interacting with the FS Economy API
Home-page: https://github.com/paulhampson/pyfseconomy
Author: Paul Hampson
Classifier: Programming Language :: Python :: 3
Classifier: License :: OSI Approved :: MIT License
Classifier: Operating System :: OS Independent
Classifier: Development Status :: 3 - Alpha
Classifier: Natural Language :: English
Classifier: Topic :: Games/Entertainment
Requires-Python: >=3.8
License-File: LICENSE
Requires-Dist: pandas (~=1.5.2)
Requires-Dist: requests (~=2.28.1)
Requires-Dist: geographiclib (~=2.0)
